.coveragerc
.gitignore
.readthedocs.yml
AUTHORS.md
CHANGELOG.md
CONTRIBUTING.md
LICENSE.txt
MANIFEST.in
README.md
pyproject.toml
setup.cfg
setup.py
tox.ini
.github/workflows/pypi-test.yml
extern/fetch.sh
src/dolomite_schemas/__init__.py
src/dolomite_schemas/includes.py
src/dolomite_schemas.egg-info/PKG-INFO
src/dolomite_schemas.egg-info/SOURCES.txt
src/dolomite_schemas.egg-info/dependency_links.txt
src/dolomite_schemas.egg-info/not-zip-safe
src/dolomite_schemas.egg-info/requires.txt
src/dolomite_schemas.egg-info/top_level.txt
src/dolomite_schemas/schemas/amalgamated_array/v1.json
src/dolomite_schemas/schemas/array/v1.json
src/dolomite_schemas/schemas/atomic_vector/v1.json
src/dolomite_schemas/schemas/atomic_vector_list/v1.json
src/dolomite_schemas/schemas/bam_file/v1.json
src/dolomite_schemas/schemas/bam_index_file/v1.json
src/dolomite_schemas/schemas/bed_file/v1.json
src/dolomite_schemas/schemas/bgzip_index_file/v1.json
src/dolomite_schemas/schemas/bigbed_file/v1.json
src/dolomite_schemas/schemas/bigwig_file/v1.json
src/dolomite_schemas/schemas/bumpy_data_frame_matrix/v1.json
src/dolomite_schemas/schemas/bumpy_matrix/v1.json
src/dolomite_schemas/schemas/compressed_list/v1.json
src/dolomite_schemas/schemas/csv_data_frame/v1.json
src/dolomite_schemas/schemas/data_frame/v1.json
src/dolomite_schemas/schemas/data_frame_factor/v1.json
src/dolomite_schemas/schemas/data_frame_list/v1.json
src/dolomite_schemas/schemas/dataset/v1.json
src/dolomite_schemas/schemas/design_matrix/v1.json
src/dolomite_schemas/schemas/fa_index_file/v1.json
src/dolomite_schemas/schemas/factor/v1.json
src/dolomite_schemas/schemas/fasta_file/v1.json
src/dolomite_schemas/schemas/fastq_file/v1.json
src/dolomite_schemas/schemas/generic_document/v1.json
src/dolomite_schemas/schemas/generic_file/v1.json
src/dolomite_schemas/schemas/generic_object/v1.json
src/dolomite_schemas/schemas/genomic_ranges/v1.json
src/dolomite_schemas/schemas/genomic_ranges_list/v1.json
src/dolomite_schemas/schemas/gff_file/v1.json
src/dolomite_schemas/schemas/gmt_file/v1.json
src/dolomite_schemas/schemas/hdf5_data_frame/v1.json
src/dolomite_schemas/schemas/hdf5_delayed_array/v1.json
src/dolomite_schemas/schemas/hdf5_dense_array/v1.json
