Metadata-Version: 2.1
Name: dolomite-schemas
Version: 0.0.7
Summary: JSON schemas for bioconductor objects.
Home-page: https://github.com/ArtifactDB/dolomite-schemas
Author: Jayaram Kancherla
Author-email: jayaram.kancherla@gmail.com
License: MIT
Project-URL: Documentation, https://github.com/ArtifactDB/dolomite-schemas
Platform: any
Classifier: Development Status :: 4 - Beta
Classifier: Programming Language :: Python
License-File: LICENSE.txt
Requires-Dist: importlib-metadata; python_version < "3.8"
Provides-Extra: testing
Requires-Dist: setuptools; extra == "testing"
Requires-Dist: pytest; extra == "testing"
Requires-Dist: pytest-cov; extra == "testing"
